MANIFEST.in
requirements.txt
setup.py
test_requirements.txt
version.txt
cloudshell/__init__.py
cloudshell/cm/__init__.py
cloudshell/cm/ansible/__init__.py
cloudshell/cm/ansible/ansible_shell.py
cloudshell/cm/ansible/domain/__init__.py
cloudshell/cm/ansible/domain/ansible_command_executor.py
cloudshell/cm/ansible/domain/ansible_config_file.py
cloudshell/cm/ansible/domain/ansible_configuration.py
cloudshell/cm/ansible/domain/cancellation_sampler.py
cloudshell/cm/ansible/domain/connection_service.py
cloudshell/cm/ansible/domain/exceptions.py
cloudshell/cm/ansible/domain/file_system_service.py
cloudshell/cm/ansible/domain/filename_extractor.py
cloudshell/cm/ansible/domain/host_vars_file.py
cloudshell/cm/ansible/domain/http_request_service.py
cloudshell/cm/ansible/domain/inventory_file.py
cloudshell/cm/ansible/domain/playbook_downloader.py
cloudshell/cm/ansible/domain/stdout_accumulator.py
cloudshell/cm/ansible/domain/temp_folder_scope.py
cloudshell/cm/ansible/domain/zip_service.py
cloudshell/cm/ansible/domain/Helpers/__init__.py
cloudshell/cm/ansible/domain/Helpers/ansible_connection_helper.py
cloudshell/cm/ansible/domain/output/__init__.py
cloudshell/cm/ansible/domain/output/ansible_result.py
cloudshell/cm/ansible/domain/output/unixToHtmlConverter.py
cloudshell_cm_ansible.egg-info/PKG-INFO
cloudshell_cm_ansible.egg-info/SOURCES.txt
cloudshell_cm_ansible.egg-info/dependency_links.txt
cloudshell_cm_ansible.egg-info/requires.txt
cloudshell_cm_ansible.egg-info/top_level.txt
tests/__init__.py
tests/helpers.py
tests/test_ansible_command_executor.py
tests/test_ansible_config_file.py
tests/test_ansible_configutarion.py
tests/test_ansible_result.py
tests/test_ansible_shell.py
tests/test_filename_extractor.py
tests/test_host_vars_file.py
tests/test_inventory_file.py
tests/test_output_writer.py
tests/test_playbook_downloader.py
tests/test_temp_folder_scope.py
tests/test_unixToHtml_converter.py
tests/test_zip_service.py
tests/mocks/__init__.py
tests/mocks/file_system_service_mock.py